[{"__symbolic":"module","version":4,"metadata":{"UifPersonaCardComponent":{"__symbolic":"class","decorators":[{"__symbolic":"call","expression":{"__symbolic":"reference","module":"@angular/core","name":"Component","line":5,"character":1},"arguments":[{"selector":"uif-persona-card","templateUrl":"./uif-persona-card.component.html","styleUrls":["./uif-persona-card.component.scss"]}]}],"members":{"personaCard":[{"__symbolic":"property","decorators":[{"__symbolic":"call","expression":{"__symbolic":"reference","module":"@angular/core","name":"Input","line":11,"character":2}}]}]}}}}]