[{"__symbolic":"module","version":4,"metadata":{"UifOverlayComponent":{"__symbolic":"class","decorators":[{"__symbolic":"call","expression":{"__symbolic":"reference","module":"@angular/core","name":"Component","line":2,"character":1},"arguments":[{"selector":"uif-overlay","templateUrl":"./uif-overlay.component.html","styleUrls":["./uif-overlay.component.scss"]}]}],"members":{"isOpen":[{"__symbolic":"property","decorators":[{"__symbolic":"call","expression":{"__symbolic":"reference","module":"@angular/core","name":"Input","line":8,"character":2}}]}],"isDark":[{"__symbolic":"property","decorators":[{"__symbolic":"call","expression":{"__symbolic":"reference","module":"@angular/core","name":"Input","line":9,"character":2}}]}]}}}}]