[{"__symbolic":"module","version":4,"metadata":{"UifMessageBannerComponent":{"__symbolic":"class","decorators":[{"__symbolic":"call","expression":{"__symbolic":"reference","module":"@angular/core","name":"Component","line":2,"character":1},"arguments":[{"selector":"uif-message-banner","templateUrl":"./uif-message-banner.component.html","styleUrls":["./uif-message-banner.component.scss","../uif-fabric.shared.scss"]}]}],"members":{"isOpen":[{"__symbolic":"property","decorators":[{"__symbolic":"call","expression":{"__symbolic":"reference","module":"@angular/core","name":"Input","line":11,"character":2}}]}],"isOpenChange":[{"__symbolic":"property","decorators":[{"__symbolic":"call","expression":{"__symbolic":"reference","module":"@angular/core","name":"Output","line":12,"character":2}}]}],"hasOverlay":[{"__symbolic":"property","decorators":[{"__symbolic":"call","expression":{"__symbolic":"reference","module":"@angular/core","name":"Input","line":13,"character":2}}]}],"isClosable":[{"__symbolic":"property","decorators":[{"__symbolic":"call","expression":{"__symbolic":"reference","module":"@angular/core","name":"Input","line":14,"character":2}}]}],"closePane":[{"__symbolic":"method"}]}}}}]